Metadata-Version: 2.1
Name: anutils
Version: 0.4.5
Summary: ml and single cell utils.
Home-page: https://github.com/AaronNing/anutils
Author: Aaron Ning
Author-email: aaronning98@gmail.com
License: MIT
Keywords: anutils
